rack/__init__.py
rack/dict.py
rack/dict_lmdb.py
rack/dict_sqlite3.py
rack/set.py
rack/set_lmdb.py
rack/set_lmdb_small.py
rack-0.1.4.dist-info/METADATA
rack-0.1.4.dist-info/WHEEL
rack-0.1.4.dist-info/top_level.txt
rack-0.1.4.dist-info/RECORD
