Metadata-Version: 2.1
Name: rack
Version: 0.1.4
Summary: Persistent data structures mimicking as Python native containers
Author: Jérôme Carretero
License: MIT License
Project-URL: Homepage, https://gitlab.com/cJ/rack
Project-URL: Download, https://pypi.python.org/pypi/rack
Keywords: persistent
Classifier: License :: OSI Approved :: MIT License
Classifier: Programming Language :: Python :: 3
Classifier: Intended Audience :: Developers
